README.md
setup.py
sutils/__init__.py
sutils/debug.py
sutils/decorators.py
sutils/utils.py
sutils.egg-info/PKG-INFO
sutils.egg-info/SOURCES.txt
sutils.egg-info/dependency_links.txt
sutils.egg-info/not-zip-safe
sutils.egg-info/top_level.txt